asai/__init__.py
asai/_backend.py
asai/_cli.py
asai/models.py
asai-0.3.1.dist-info/LICENSE
asai-0.3.1.dist-info/METADATA
asai-0.3.1.dist-info/WHEEL
asai-0.3.1.dist-info/entry_points.txt
asai-0.3.1.dist-info/top_level.txt
asai-0.3.1.dist-info/RECORD
