Metadata-Version: 2.1
Name: asai
Version: 0.3.1
Summary: ASAI can find the available actions, conditions, and other useful IAM information for AWS services.
Home-page: https://github.com/inhumantsar/asai
Author: Shaun Martin
Author-email: inhumantsar@protonmail.com
License: BSD License
Download-URL: https://github.com/inhumantsar/asai/archive/refs/tags/v0.3.1.zip
Project-URL: Repository, https://github.com/inhumantsar/asai
Project-URL: Bug Reports, https://github.com/inhumantsar/asai/issues
Keywords: aws,iam,amazon web services
Platform: any
Classifier: Development Status :: 4 - Beta
Classifier: Intended Audience :: Developers
Classifier: License :: OSI Approved :: MIT License
Classifier: Operating System :: OS Independent
Classifier: Programming Language :: Python :: 3.6
Classifier: Programming Language :: Python :: 3.7
Classifier: Programming Language :: Python :: 3.8
Classifier: Programming Language :: Python :: 3.9
Classifier: Topic :: Utilities
Requires-Python: >=3.6.0
License-File: LICENSE
Requires-Dist: fuzzywuzzy (>=0.18.0)
Requires-Dist: click (>=8.0.1)
Requires-Dist: requests (>=2.26.0)
